mypythonlib/__init__.py
mypythonlib/myfunctions.py
printlibtest-0.1.dist-info/METADATA
printlibtest-0.1.dist-info/WHEEL
printlibtest-0.1.dist-info/top_level.txt
printlibtest-0.1.dist-info/RECORD
